bitte/__init__.py
bitte/asyncronous_call_utils.py
bitte/example.py
bitte-0.0.1.dist-info/METADATA
bitte-0.0.1.dist-info/WHEEL
bitte-0.0.1.dist-info/top_level.txt
bitte-0.0.1.dist-info/RECORD
