Metadata-Version: 2.1
Name: bitte
Version: 0.0.1
Summary: A way to quickly preprocess common NLP tasks. Specialised for english tasks requiring lightweight compute that you just want done
Author-email: Bitte Development Team <pythonmodule@bitteapi.com>
Project-URL: Homepage, https://github.com/bitteauthor/bitteapi
Project-URL: Bug Tracker, https://github.com/bitteauthor/bitteapi/issues
Classifier: Programming Language :: Python :: 3
Classifier: License :: OSI Approved :: MIT License
Classifier: Operating System :: OS Independent
Requires-Python: >=3.7
